tranche/__init__.py
tranche/py.typed
tranche/section.py
tranche/tranche.py
tranche/version.py
tranche-0.4.0.dist-info/licenses/LICENSE
tranche-0.4.0.dist-info/METADATA
tranche-0.4.0.dist-info/WHEEL
tranche-0.4.0.dist-info/top_level.txt
tranche-0.4.0.dist-info/RECORD
