Metadata-Version: 2.4
Name: tranche
Version: 0.4.0
Summary: ConfigParser with layered precedence, provenance, comment-preserving writes, and safe expressions.
Author: Xylar Asay-Davis
License-Expression: BSD-3-Clause
Project-URL: Homepage, https://github.com/xylar/tranche
Project-URL: Documentation, https://xylar.github.io/tranche/
Project-URL: Issues, https://github.com/xylar/tranche/issues
Keywords: config,configparser,layered,provenance,numpy,safe-eval
Classifier: Programming Language :: Python :: 3
Classifier: Programming Language :: Python :: 3 :: Only
Classifier: Operating System :: OS Independent
Classifier: Typing :: Typed
Requires-Python: >=3.10
License-File: LICENSE
Provides-Extra: numpy
Requires-Dist: numpy>=1.22; extra == "numpy"
Provides-Extra: dev
Requires-Dist: build>=1.3; extra == "dev"
Requires-Dist: pre-commit>=3.5; extra == "dev"
Requires-Dist: pytest>=7.4; extra == "dev"
Requires-Dist: pytest-cov>=4.1; extra == "dev"
Requires-Dist: twine>=6.0; extra == "dev"
Requires-Dist: wheel>=0.45; extra == "dev"
Provides-Extra: docs
Requires-Dist: furo>=2023.9.10; extra == "docs"
Requires-Dist: myst-parser>=2.0; extra == "docs"
Requires-Dist: sphinx>=7.0; extra == "docs"
Requires-Dist: tomli>=2.0; python_version < "3.11" and extra == "docs"
Dynamic: license-file
